pycool/__init__.py
pycool-0.4.dist-info/METADATA
pycool-0.4.dist-info/WHEEL
pycool-0.4.dist-info/top_level.txt
pycool-0.4.dist-info/RECORD
