Metadata-Version: 2.1
Name: pycool
Version: 0.4
Summary: simple script library
Home-page: http://github.com/anisg/pytool
Author: A G
Author-email: nope@nope.com
License: MIT
Platform: UNKNOWN
